{
  "tx_id": "TXDEMO-CLEAN-CROSSBORDER",
  "timestamp": "2026-06-14T10:00:00",
  "channel": "SWIFT",
  "amount_inr": "200000",
  "sender_account_id": "ACC29699",
  "sender_name": "Suresh Bose",
  "sender_pan": "VVLKR4510I",
  "sender_dob": "1975-06-14",
  "sender_bank": "ICIC",
  "sender_ifsc": "ICIC0000861",
  "sender_vpa": "acc29699@okicici",
  "receiver_account_id": "EXT40010",
  "receiver_name": "University of Toronto",
  "receiver_pan": "",
  "receiver_dob": "",
  "receiver_bank": "FOREIGN",
  "receiver_vpa": "",
  "receiver_state": "",
  "receiver_city": "Toronto",
  "tx_location_city": "New Delhi",
  "tx_location_state": "DL",
  "tx_location_country": "IN",
  "tx_location_lat": "28.6139",
  "tx_location_lon": "77.2090",
  "device_id": "DEV-ACC29699",
  "purpose_code": "P0801",
  "is_cross_border": "1",
  "fx_usd_inr": "83.2",
  "usd_equiv": "2404",
  "beneficiary_id": "BENE-EDU-1",
  "tx_status": "SUCCESS"
}
